{"v":0,"docs":{"intro--docs":{"id":"intro--docs","name":"Docs","path":"./src/stories/0-intro.mdx","title":"Intro","content":"import { Meta, Description, Markdown } from '@storybook/addon-docs/blocks';\n\nimport markdown from '../../README.md?raw';\n\n<Meta title=\"Intro\" />\n\n<Markdown>{markdown}</Markdown>\n"},"style-colors--docs":{"id":"style-colors--docs","name":"Docs","path":"./src/stories/colors.mdx","title":"Style/Colors","content":"import { Meta, ColorPalette, ColorItem } from '@storybook/addon-docs/blocks';\n\n<Meta title=\"Style/Colors\" />\n\n# Colors\n\n## Palettes\n\n<ColorPalette>\n  <ColorItem\n    title=\"Blue\"\n    subtitle=\"--mg-b-color-blue-##\"\n    colors={{\n      '10': 'rgb(227 244 255)',\n      '20': 'rgb(209 237 255)',\n      '30': 'rgb(166 219 255)',\n      '40': 'rgb(106 195 255)',\n      '50': 'rgb(64 179 255)',\n      '60': 'rgb(22 162 255)',\n      '70': 'rgb(0 132 220)',\n      '80': 'rgb(0 94 156)',\n      '90': 'rgb(0 67 111)',\n      '100': 'rgb(0 39 66)',\n    }}\n  />\n  <ColorItem\n    title=\"Green\"\n    subtitle=\"--mg-b-color-green-##\"\n    colors={{\n      '10': 'rgb(234 251 244)',\n      '20': 'rgb(212 247 234)',\n      '30': 'rgb(181 240 219)',\n      '40': 'rgb(144 232 202)',\n      '50': 'rgb(97 223 179)',\n      '60': 'rgb(50 213 156)',\n      '70': 'rgb(46 194 142)',\n      '80': 'rgb(36 151 111)',\n      '90': 'rgb(21 89 66)',\n      '100': 'rgb(13 54 40)',\n    }}\n  />\n  <ColorItem\n    title=\"Red\"\n    subtitle=\"--mg-b-color-red-##\"\n    colors={{\n      '10': 'rgb(251 233 234)',\n      '20': 'rgb(248 216 217)',\n      '30': 'rgb(242 174 178)',\n      '40': 'rgb(236 134 139)',\n      '50': 'rgb(229 96 103)',\n      '60': 'rgb(221 42 52)',\n      '70': 'rgb(219 31 41)',\n      '80': 'rgb(152 21 28)',\n      '90': 'rgb(120 17 23)',\n      '100': 'rgb(92 13 13)',\n    }}\n  />\n  <ColorItem\n    title=\"Yellow\"\n    subtitle=\"--mg-b-color-yellow-##\"\n    colors={{\n      '10': 'rgb(255 247 230)',\n      '20': 'rgb(255 240 207)',\n      '30': 'rgb(255 226 162)',\n      '40': 'rgb(255 212 118)',\n      '50': 'rgb(255 195 62)',\n      '60': 'rgb(232 177 56)',\n      '70': 'rgb(181 138 44)',\n      '80': 'rgb(140 107 34)',\n      '90': 'rgb(86 66 21)',\n      '100': 'rgb(53 41 13)',\n    }}\n  />\n  <ColorItem\n    title=\"Neutral\"\n    subtitle=\"--mg-b-color-neutral-##\"\n    colors={{\n      '0': 'rgb(255 255 255)',\n      '10': 'rgb(250 251 251)',\n      '20': 'rgb(236 238 238)',\n      '30': 'rgb(225 227 228)',\n      '40': 'rgb(197 201 203)',\n      '50': 'rgb(182 188 190)',\n      '60': 'rgb(157 165 167)',\n      '70': 'rgb(129 139 142)',\n      '80': 'rgb(101 113 117)',\n      '90': 'rgb(75 89 94)',\n      '100': 'rgb(47 64 69)',\n      '110': 'rgb(21 40 46)',\n      '120': 'rgb(5 9 11)',\n    }}\n  />\n</ColorPalette>\n\n## Semantic colors\n\n<ColorPalette>\n  <ColorItem\n    title=\"Danger\"\n    subtitle=\"--mg-b-color-danger\"\n    colors={{\n      '--mg-b-color-red-70': 'rgb(219 31 41)',\n    }}\n  />\n  <ColorItem\n    title=\"Info\"\n    subtitle=\"--mg-b-color-info\"\n    colors={{\n      '--mg-b-color-blue-80': 'rgb(0 94 156)',\n    }}\n  />\n  <ColorItem\n    title=\"Success\"\n    subtitle=\"--mg-b-color-success\"\n    colors={{\n      '--mg-b-color-green-60': 'rgb(50 213 156)',\n    }}\n  />\n  <ColorItem\n    title=\"Warning\"\n    subtitle=\"--mg-b-color-warning\"\n    colors={{\n      '--mg-b-color-yellow-50': 'rgb(255 195 62)',\n    }}\n  />\n</ColorPalette>\n\n## Brand colors\n\n<ColorPalette>\n  <ColorItem\n    title=\"Primary\"\n    subtitle=\"--mg-b-color-primary\"\n    colors={{\n      '--mg-b-color-neutral-110': 'rgb(21 40 46)',\n    }}\n  />\n  <ColorItem\n    title=\"Secondary\"\n    subtitle=\"--mg-b-color-secondary\"\n    colors={{\n      '--mg-b-color-neutral-10': 'rgb(250 251 251)',\n    }}\n  />\n  <ColorItem\n    title=\"App\"\n    subtitle=\"--mg-b-color-app\"\n    colors={{\n      '--mg-b-color-blue-80': 'rgb(0 94 156)',\n    }}\n  />\n</ColorPalette>\n\n## Neutrals colors\n\n<ColorPalette>\n  <ColorItem\n    title=\"Dark\"\n    subtitle=\"--mg-b-color-dark\"\n    colors={{\n      '--mg-b-color-neutral-110': 'rgb(21 40 46)',\n    }}\n  />\n  <ColorItem\n    title=\"Light\"\n    subtitle=\"--mg-b-color-light\"\n    colors={{\n      '--mg-b-color-neutral-0': 'rgb(255 255 255)',\n    }}\n  />\n</ColorPalette>\n"},"style-custom-properties--docs":{"id":"style-custom-properties--docs","name":"Docs","path":"./src/stories/custom-properties.mdx","title":"Style/Custom Properties","content":"import { Meta } from '@storybook/addon-docs/blocks';\n\n<Meta title=\"Style/Custom Properties\" />\n\n# Custom Properties\n\nTo customize our components we are using [Custom Properties](https://developer.mozilla.org/en-US/docs/Web/CSS/Using_CSS_custom_properties).\n\nCustom properties are included in our stylesheets.\n\n## How to Customize\n\nCustom properties customization must be done after the stylesheets import.\n\n### Global\n\nFor a global customization, you will prefer to use the `:root` selector:\n\n```css\n:root {\n  /* font */\n  --font-size: 1.4rem;\n  --line-height: 1.5;\n  --font-family: 'Ubuntu';\n  --font-family-heading: 'Montserrat';\n  /* mg-button */\n  --mg-button-border-radius: var(--mg-b-size-radius);\n  /* mg-tooltip */\n  --mg-c-tooltip-border-radius: var(--mg-b-size-radius);\n  --mg-c-tooltip-color-background: var(--mg-b-color-dark);\n  ...\n}\n```\n\n### Localized\n\nWhen your web component needs to be customized only in a localized area, you will prefer to use a CSS selector:\n\n```html\n<!-- Style -->\n<style>\n  .message-without-radius {\n    --mg-c-message-border-radius: 0;\n  }\n</style>\n\n<!-- On component -->\n<mg-message class=\"message-without-radius\">This message should not have radius</mg-message>\n\n<!-- or on a defined area -->\n<div class=\"message-without-radius\">\n  <mg-message>This message should not have radius</mg-message>\n  <mg-message>This message also</mg-message>\n</div>\n```\n\n## More custom properties\n\nOther custom properties are available.\n\nComponents like [`mg-form`](https://gitlab.mgdis.fr/core/core-ui/core-ui/-/blob/master/packages/styles/scss/components/mg-form.scss) will define variables to set how `mg-input-*` will be displayed.\n\nOther components like [`mg-button`](https://gitlab.mgdis.fr/core/core-ui/core-ui/-/blob/master/packages/styles/scss/components/mg-button.scss) or [`mg-input-*`](https://gitlab.mgdis.fr/core/core-ui/core-ui/-/blob/master/packages/styles/scss/components/_mg-input-box.scss) can be customized using custom properties but are using the fallback value (ex: `text-align: var(--mg-c-input-text-align, left);`).\n"},"style-icons--docs":{"id":"style-icons--docs","name":"Docs","path":"./src/stories/icons.mdx","title":"Style/Icons","content":"import { Meta } from '@storybook/addon-docs/blocks';\nimport IconGallery from './icon-gallery';\n\n<Meta title=\"Style/Icons\" />\n\n# Icons\n\n<IconGallery />\n"},"getting-started--docs":{"id":"getting-started--docs","name":"Docs","path":"./src/stories/1-getting-started.mdx","title":"Getting started","content":"import { Meta, Description, Markdown } from '@storybook/addon-docs/blocks';\n\nimport markdown from '../../GETTING-STARTED.md?raw';\n\n<Meta title=\"Getting started\" />\n\n<Markdown>{markdown}</Markdown>\n"},"changelog--docs":{"id":"changelog--docs","name":"Docs","path":"./src/stories/2-changelog.mdx","title":"Changelog","content":"import { Meta, Description, Markdown } from '@storybook/addon-docs/blocks';\n\nimport changelog from '../../CHANGELOG.md?raw';\n\n<Meta title=\"Changelog\" />\n\n<Markdown>{changelog}</Markdown>\n"},"breaking-changes--docs":{"id":"breaking-changes--docs","name":"Docs","path":"./src/stories/3-breaking-changes.mdx","title":"Breaking changes","content":"import { Meta, Description, Markdown } from '@storybook/addon-docs/blocks';\n\nimport markdown from '../../BREAKING-CHANGES.md?raw';\n\n<Meta title=\"Breaking changes\" />\n\n<Markdown>{markdown}</Markdown>\n"}}}